
{
    "comment" : "This file is used to help set default values when using the dotnet CLI extension Amazon.ElasticBeanstalk.Tools. For more information run \"dotnet eb --help\" from the project root.",
    "profile" : "vs_code_deploy",
    "region"  : "us-east-2",
    "application" : "SampleAWSCore",
    "environment" : "SampleAWSCore-dev",
    "cname"       : "sampleawscore-dev",
    "solution-stack" : "64bit Windows Server 2019 v2.6.2 running IIS 10.0",
    "environment-type" : "SingleInstance",
    "instance-profile" : "aws-elasticbeanstalk-ec2-role",
    "service-role"     : "aws-elasticbeanstalk-service-role",
    "health-check-url" : "/",
    "instance-type"    : "t3a.medium",
    "key-pair"         : "",
    "iis-website"      : "Default Web Site",
    "app-path"         : "/",
    "enable-xray"      : false,
    "configuration"    : "Debug",
    "framework"        : "netcoreapp3.1",
    "self-contained"   : false,
    "enhanced-health-type" : "basic",
    "additional-options"   : "\"aws:autoscaling:launchconfiguration,SecurityGroups\"=\"sg-87bc9be1\";\"aws:ec2:vpc,Subnets\"=\"subnet-82bb51dd\"",
    "proxy-server"         : "nginx"
}